Workbook

Sheet Sales Report
A1: DAILY SALES REPORT
A2: Periode : | B2: 01/06/2026 - 03/06/2026
D4: POS | N4: Payment Method / Merchant Report
A5: Date | B5: Store | C5: Platform | D5: Gross Amount Excl (Mrs. Puff) | E5: Gross Amount Excl (Pup Pup Boogie) | F5: Gross Amount Excl (DIY Activity) | G5: Gross Amount Excl (Photo Printing) | H5: Gross Amount Excl (Coin Changer) | I5: Discount | J5: Net Sales | K5: Service Charge | L5: Tax | M5: Gross Sales (All incl) | N5: BRI | O5: BCA | P5: Nusapay | Q5: Starthing | R5: Deposit | S5: Voucher | T5: Total | U5: Diff
A6: 46174 | B6: OUTLET01-Park Nickelodeon | C6: Activity | D6: 0 | E6: 0 | F6: 545455 | J6: =SUM(D6:H6)-I6 -> 545455 | L6: 54545 | M6: =J6+K6+L6 -> 600000 | P6: 600000 | R6: 0 | S6: 0 | T6: =SUM(N6:S6) -> 600000 | U6: =M6-T6 -> 0
A7: 46175 | B7: OUTLET01-Park Nickelodeon | C7: Activity | F7: 136364 | J7: =SUM(D7:H7)-I7 -> 136364 | L7: 13636 | M7: =J7+K7+L7 -> 150000 | P7: 150000 | R7: 0 | S7: 0 | T7: =SUM(N7:S7) -> 150000 | U7: =M7-T7 -> 0
A8: 46176 | B8: OUTLET01-Park Nickelodeon | C8: Activity | F8: 318182 | J8: =SUM(D8:H8)-I8 -> 318182 | L8: 31818 | M8: =J8+K8+L8 -> 350000 | P8: 350000 | R8: 0 | S8: 0 | T8: =SUM(N8:S8) -> 350000 | U8: =M8-T8 -> 0
A9: 46174 | B9: OUTLET02-Nickelodeon Theme Park Carstensz Mall | C9: Activity | E9: 90910 | J9: =SUM(D9:H9)-I9 -> 90910 | L9: 9090 | M9: =J9+K9+L9 -> 100000 | P9: 100000 | R9: 0 | S9: 0 | T9: =SUM(N9:S9) -> 100000 | U9: =M9-T9 -> 0
A10: 46175 | B10: OUTLET02-Nickelodeon Theme Park Carstensz Mall | C10: Activity | J10: =SUM(D10:H10)-I10 -> 0 | M10: =J10+K10+L10 -> 0 | R10: 0 | S10: 0 | T10: =SUM(N10:S10) -> 0 | U10: =M10-T10 -> 0
A11: 46176 | B11: OUTLET02-Nickelodeon Theme Park Carstensz Mall | C11: Activity | J11: =SUM(D11:H11)-I11 -> 0 | M11: =J11+K11+L11 -> 0 | R11: 0 | S11: 0 | T11: =SUM(N11:S11) -> 0 | U11: =M11-T11 -> 0
B13: TOTAL | D13: =SUM(D6:D12) -> 0 | E13: =SUM(E6:E12) -> 90910 | I13: =SUM(I6:I12) -> 0 | J13: =SUM(J6:J12) -> 1090911 | K13: =SUM(K6:K12) -> 0 | L13: =SUM(L6:L12) -> 109089 | M13: =SUM(M6:M12) -> 1200000 | N13: =SUM(N6:N12) -> 0 | O13: =SUM(O6:O12) -> 0 | P13: =SUM(P6:P12) -> 1200000 | R13: =SUM(R6:R12) -> 0 | S13: =SUM(S6:S12) -> 0 | T13: =SUM(T6:T12) -> 1200000 | U13: =SUM(U6:U12) -> 0

Sheet Merchant Report
A1: MERCHANT REPORT
A2: Periode : | B2: 01/06/2026 - 03/06/2026
A4: Date | B4: Store | C4: Platform | D4: BRI | G4: BCA | J4: NUSAPAY | M4: DEPOSIT | P4: TOTAL
D5: Amont Transaction | E5: MDR | F5: Net Amount | G5: Amont Transaction | H5: MDR | I5: Net Amount | J5: Amont Transaction | K5: MDR | L5: Net Amount | M5: Amont Transaction | N5: MDR | O5: Net Amount | P5: Amont Transaction | Q5: MDR | R5: Net Amount
A6: 46174 | B6: OUTLET01-Park Nickelodeon | C6: Activity | F6: =D6-E6 -> 0 | I6: =G6-H6 -> 0 | J6: ='Sales Report'!P6 -> 600000 | K6: 4200 | L6: =J6-K6 -> 595800 | P6: =D6+G6+J6+M6 -> 600000 | Q6: =E6+H6+K6+N6 -> 4200 | R6: =F6+I6+L6+O6 -> 595800
A7: 46175 | B7: OUTLET01-Park Nickelodeon | C7: Activity | F7: =D7-E7 -> 0 | I7: =G7-H7 -> 0 | J7: ='Sales Report'!P7 -> 150000 | K7: 1050 | L7: =J7-K7 -> 148950 | P7: =D7+G7+J7+M7 -> 150000 | Q7: =E7+H7+K7+N7 -> 1050 | R7: =F7+I7+L7+O7 -> 148950
A8: 46176 | B8: OUTLET01-Park Nickelodeon | C8: Activity | F8: =D8-E8 -> 0 | I8: =G8-H8 -> 0 | J8: ='Sales Report'!P8 -> 350000 | K8: 2450 | L8: =J8-K8 -> 347550 | P8: =D8+G8+J8+M8 -> 350000 | Q8: =E8+H8+K8+N8 -> 2450 | R8: =F8+I8+L8+O8 -> 347550
A9: 46174 | B9: OUTLET02-Nickelodeon Theme Park Carstensz Mall | C9: Activity | F9: =D9-E9 -> 0 | I9: =G9-H9 -> 0 | J9: ='Sales Report'!P9 -> 100000 | K9: 700 | L9: =J9-K9 -> 99300 | P9: =D9+G9+J9+M9 -> 100000 | Q9: =E9+H9+K9+N9 -> 700 | R9: =F9+I9+L9+O9 -> 99300
A10: 46175 | B10: OUTLET02-Nickelodeon Theme Park Carstensz Mall | C10: Activity | F10: =D10-E10 -> 0 | I10: =G10-H10 -> 0 | J10: ='Sales Report'!P10 -> 0 | K10: 0 | L10: =J10-K10 -> 0 | P10: =D10+G10+J10+M10 -> 0 | Q10: =E10+H10+K10+N10 -> 0 | R10: =F10+I10+L10+O10 -> 0
A11: 46176 | B11: OUTLET02-Nickelodeon Theme Park Carstensz Mall | C11: Activity | F11: =D11-E11 -> 0 | I11: =G11-H11 -> 0 | J11: ='Sales Report'!P11 -> 0 | K11: 0 | L11: =J11-K11 -> 0 | P11: =D11+G11+J11+M11 -> 0 | Q11: =E11+H11+K11+N11 -> 0 | R11: =F11+I11+L11+O11 -> 0
B13: TOTAL | D13: =SUM(D6:D12) -> 0 | E13: =SUM(E6:E12) -> 0 | F13: =SUM(F6:F12) -> 0 | G13: =SUM(G6:G12) -> 0 | H13: =SUM(H6:H12) -> 0 | I13: =SUM(I6:I12) -> 0 | J13: =SUM(J6:J12) -> 1200000 | K13: =SUM(K6:K12) -> 8400 | ... R13: =SUM(R6:R12) -> 1191600
