Workbook

Sheet Contoh Sales Report Walk In
A1: DAILY SALES REPORT
A2: Periode : | B2: 01/06/2026 - 03/06/2026
D4: POS | J4: Payment Method / Merchant Report
A5: Date | B5: Store | C5: Platform | D5: Gross Amount Excl. | E5: Discount | F5: Net Sales | G5: Tax | H5: Charge | I5: Gross Sales (All incl) | J5: BRI | K5: BCA | L5: Nusapay | M5: Deposit | N5: Voucher | O5: Total | P5: Diff
A6: 46174 | B6: Carstensz Paw Patrol | C6: Walk In Ticket | D6: =17910000/1.1 -> 16281818 | E6: 0 | F6: =D6-E6 -> 16281818 | G6: 1628181.8 | H6: 0 | I6: =F6+G6+H6 -> 17910000 | J6: 9520000 | K6: 8390000 | L6: 0 | M6: 0 | N6: 0 | O6: =SUM(J6:N6) -> 17910000 | P6: =I6-O6 -> 0
A7: 46175 | B7: Carstensz Paw Patrol | C7: Walk In Ticket | D7: 2554545.5 | E7: 0 | F7: =D7-E7 -> 2554545.5 | G7: 255454.55 | H7: 0 | I7: =F7+G7+H7 -> 2810000 | J7: 930000 | K7: 1880000 | L7: 0 | M7: 0 | N7: 0 | O7: =SUM(J7:N7) -> 2810000 | P7: =I7-O7 -> 0
A8: 46176 | B8: Carstensz Paw Patrol | C8: Walk In Ticket | D8: 1236363.6 | E8: 0 | F8: =D8-E8 -> 1236363.6 | G8: 123636.36 | H8: 0 | I8: =F8+G8+H8 -> 1360000 | J8: 780000 | K8: 580000 | L8: 0 | M8: 0 | N8: 0 | O8: =SUM(J8:N8) -> 1360000 | P8: =I8-O8 -> 0
B11: TOTAL | D11: =SUM(D6:D10) -> 20072727 | E11: =SUM(E6:E10) -> 0 | F11: =SUM(F6:F10) -> 20072727 | G11: =SUM(G6:G10) -> 2007272.7 | H11: =SUM(H6:H10) -> 0 | I11: =SUM(I6:I10) -> 22080000 | J11: =SUM(J6:J10) -> 11230000 | K11: =SUM(K6:K10) -> 10850000 | ... M11: =SUM(M6:M10) -> 0 | O11: =SUM(O6:O10) -> 22080000 | P11: =SUM(P6:P10) -> 0

Sheet Contoh Sales Report Cafe
A1: DAILY SALES REPORT
A2: Periode : | B2: 01/06/2026 - 03/06/2026
D4: POS | N4: Payment Method / Merchant Report
A5: Date | B5: Store | C5: Platform | D5: Gross Amount Excl (Food) | E5: Gross Amount Excl (Beverage) | F5: Discount (Food) | G5: Discount (Beverage) | H5: Net Sales (Food) | I5: Net Sales (Beverage) | J5: Service Charge (Food) | K5: Service Charge (Beverage) | L5: Tax | M5: Gross Sales (All incl) | N5: BRI | O5: BCA | P5: Nusapay | Q5: Deposit | R5: Voucher | S5: Total | T5: Diff
A6: 46174 | B6: Mr. Porter Café Carstensz | C6: Food and Beverage | D6: 4355000 | E6: 1078000 | H6: =D6-F6 -> 4355000 | I6: =E6-G6 -> 1078000 | J6: 294350 | K6: 75460 | L6: 580281 | M6: =H6+I6+J6+K6+L6 -> 6383091 | N6: 904156 | O6: 794475 | P6: 4684460 | Q6: 0 | R6: 0 | S6: =SUM(N6:R6) -> 6383091 | T6: =M6-S6 -> 0
A7: 46175 | B7: Mr. Porter Café Carstensz | C7: Food and Beverage | D7: 1355000 | E7: 335000 | F7: 292500 | G7: 39000 | H7: =D7-F7 -> 1062500 | I7: =E7-G7 -> 296000 | J7: 74375 | K7: 20720 | L7: 145359.5 | M7: =H7+I7+J7+K7+L7 -> 1598954.5 | O7: 963375 | P7: 635580 | Q7: 0 | R7: 0 | S7: =SUM(N7:R7) -> 1598955 | T7: =M7-S7 -> -0.5
A8: 46176 | B8: Mr. Porter Café Carstensz | C8: Food and Beverage | D8: 1230000 | E8: 265000 | F8: 146000 | G8: 18000 | H8: =D8-F8 -> 1084000 | I8: =E8-G8 -> 247000 | J8: 75880 | K8: 14490 | L8: 142137 | M8: =H8+I8+J8+K8+L8 -> 1563507 | N8: 162426 | O8: 945131 | P8: 455950 | Q8: 0 | R8: 0 | S8: =SUM(N8:R8) -> 1563507 | T8: =M8-S8 -> 0
A9: 46174 | B9: Garfield Café | C9: Food and Beverage | D9: 7870000 | E9: 1815000 | F9: 100000 | H9: =D9-F9 -> 7770000 | I9: =E9-G9 -> 1815000 | J9: 777000 | K9: 181500 | L9: 1054350 | M9: =H9+I9+J9+K9+L9 -> 11597850 | N9: 9676650 | O9: 490050 | P9: 10133750 | Q9: 0 | R9: 0 | S9: =SUM(N9:R9) -> 20300450 | T9: =M9-S9 -> -8702600
A10: 46175 | B10: Garfield Café | C10: Food and Beverage | D10: 1230000 | E10: 378000 | G10: 13500 | H10: =D10-F10 -> 1230000 | I10: =E10-G10 -> 364500 | J10: 123000 | K10: 36450 | L10: 175395 | M10: =H10+I10+J10+K10+L10 -> 1929345 | N10: 685465 | O10: 108900 | P10: 1134980 | Q10: 0 | R10: 0 | S10: =SUM(N10:R10) -> 1929345 | T10: =M10-S10 -> 0
A11: 46176 | B11: Garfield Café | C11: Food and Beverage | D11: 1915000 | E11: 932000 | F11: 70121.95 | G11: 29878.05 | H11: =D11-F11 -> 1844878.1 | I11: =E11-G11 -> 902121.95 | J11: 184487.81 | K11: 90212.195 | L11: 302170 | M11: =H11+I11+J11+K11+L11 -> 3323870 | N11: 1051490 | O11: 260150 | P11: 2012230 | Q11: 0 | R11: 0 | S11: =SUM(N11:R11) -> 3323870 | T11: =M11-S11 -> 0
B13: TOTAL | D13: =SUM(D6:D12) -> 17955000 | E13: =SUM(E6:E12) -> 4803000 | F13: =SUM(F6:F12) -> 608621.95 | G13: =SUM(G6:G12) -> 100378.05 | H13: =SUM(H6:H12) -> 17346378 | I13: =SUM(I6:I12) -> 4702622 | J13: =SUM(J6:J12) -> 1529092.8 | K13: =SUM(K6:K12) -> 418832.2 | ... T13: =SUM(T6:T12) -> -8702600.5

Sheet Contoh Merchant Report
A1: MERCHANT REPORT
A2: Periode : | B2: 01/06/2026 - 03/06/2026
A4: Date | B4: Store | C4: Platform | D4: BRI | G4: BCA | J4: NUSAPAY | M4: DEPOSIT | P4: TOTAL
D5: Amont Transaction | E5: MDR | F5: Net Amount | G5: Amont Transaction | H5: MDR | I5: Net Amount | J5: Amont Transaction | K5: MDR | L5: Net Amount | M5: Amont Transaction | N5: MDR | O5: Net Amount | P5: Amont Transaction | Q5: MDR | R5: Net Amount
A6: 46174 | B6: Mr. Porter Café Carstensz | C6: Food and Beverage | D6: ='Contoh Sales Report Cafe'!N6 -> 904156 | E6: 4973 | F6: =D6-E6 -> 899183 | G6: ='Contoh Sales Report Cafe'!O6 -> 794475 | H6: 4644 | I6: =G6-H6 -> 789831 | J6: ='Contoh Sales Report Cafe'!P6 -> 4684460 | K6: 32791 | L6: =J6-K6 -> 4651669 | P6: =D6+G6+J6+M6 -> 6383091 | Q6: =E6+H6+K6+N6 -> 42408 | R6: =F6+I6+L6+O6 -> 6340683
A7: 46175 | B7: Mr. Porter Café Carstensz | C7: Food and Beverage | D7: ='Contoh Sales Report Cafe'!N7 -> 0 | F7: =D7-E7 -> 0 | G7: ='Contoh Sales Report Cafe'!O7 -> 963375 | H7: 1895 | I7: =G7-H7 -> 961480 | J7: ='Contoh Sales Report Cafe'!P7 -> 635580 | K7: 4449 | L7: =J7-K7 -> 631131 | P7: =D7+G7+J7+M7 -> 1598955 | Q7: =E7+H7+K7+N7 -> 6344 | R7: =F7+I7+L7+O7 -> 1592611
A8: 46176 | B8: Mr. Porter Café Carstensz | C8: Food and Beverage | D8: ='Contoh Sales Report Cafe'!N8 -> 162426 | E8: 2112 | F8: =D8-E8 -> 160314 | G8: ='Contoh Sales Report Cafe'!O8 -> 945131 | H8: 1418 | I8: =G8-H8 -> 943713 | J8: ='Contoh Sales Report Cafe'!P8 -> 455950 | K8: 3192 | L8: =J8-K8 -> 452758 | P8: =D8+G8+J8+M8 -> 1563507 | Q8: =E8+H8+K8+N8 -> 6722 | R8: =F8+I8+L8+O8 -> 1556785
A9: 46174 | B9: Garfield Café | C9: Food and Beverage | D9: ='Contoh Sales Report Cafe'!N9 -> 9676650 | E9: 121549 | F9: =D9-E9 -> 9555101 | G9: ='Contoh Sales Report Cafe'!O9 -> 490050 | H9: 6020 | I9: =G9-H9 -> 484030 | J9: ='Contoh Sales Report Cafe'!P9 -> 10133750 | K9: 70936 | L9: =J9-K9 -> 10062814 | P9: =D9+G9+J9+M9 -> 20300450 | Q9: =E9+H9+K9+N9 -> 198505 | R9: =F9+I9+L9+O9 -> 20101945
A10: 46175 | B10: Garfield Café | C10: Food and Beverage | D10: ='Contoh Sales Report Cafe'!N10 -> 685465 | E10: 495 | F10: =D10-E10 -> 684970 | G10: ='Contoh Sales Report Cafe'!O10 -> 108900 | H10: 1416 | I10: =G10-H10 -> 107484 | J10: ='Contoh Sales Report Cafe'!P10 -> 1134980 | K10: 7945 | L10: =J10-K10 -> 1127035 | P10: =D10+G10+J10+M10 -> 1929345 | Q10: =E10+H10+K10+N10 -> 9856 | R10: =F10+I10+L10+O10 -> 1919489
A11: 46176 | B11: Garfield Café | C11: Food and Beverage | D11: ='Contoh Sales Report Cafe'!N11 -> 1051490 | E11: 9485 | F11: =D11-E11 -> 1042005 | G11: ='Contoh Sales Report Cafe'!O11 -> 260150 | H11: 390 | I11: =G11-H11 -> 259760 | J11: ='Contoh Sales Report Cafe'!P11 -> 2012230 | K11: 14086 | L11: =J11-K11 -> 1998144 | P11: =D11+G11+J11+M11 -> 3323870 | Q11: =E11+H11+K11+N11 -> 23961 | R11: =F11+I11+L11+O11 -> 3299909
B13: TOTAL | D13: =SUM(D6:D12) -> 12480187 | E13: =SUM(E6:E12) -> 138614 | F13: =SUM(F6:F12) -> 12341573 | G13: =SUM(G6:G12) -> 3562081 | H13: =SUM(H6:H12) -> 15783 | I13: =SUM(I6:I12) -> 3546298 | J13: =SUM(J6:J12) -> 19056950 | K13: =SUM(K6:K12) -> 133399 | ... R13: =SUM(R6:R12) -> 34811422

Sheet Contoh Discount Report
A1: DISCOUNT REPORT
A2: Periode : | B2: 01/06/2026 - 01/06/2026
A4: Date | B4: Store | C4: Platform | D4: No. Bill | E4: Total Discount | F4: Remark
